Workbook

Sheet Raw Data
B2: INFOSYS LIMITED - HISTORICAL FINANCIALS (₹ CRORES)
B3: Line Item | C3: FY2022 Actual | D3: FY2023 Actual | E3: FY2024 Actual | F3: Avg CAGR %
B4: REVENUE
A5: # | B5: Revenue from Operations | C5: 121641 | D5: 146767 | E5: 153670 | F5: =IFERROR((E5/C5)^(1/2)-1,0) -> 0.12396957
A7: # | B7: EXPENSES
B8: Employee Cost | C8: 63997 | D8: 78374 | E8: 82636 | F8: =IFERROR((E8/C8)^(1/2)-1,0) -> 0.13633095
B9: Selling and Admin | C9: 4305 | D9: 5300 | E9: 5705 | F9: =IFERROR((E9/C9)^(1/2)-1,0) -> 0.15117473
B10: Other Expenses | C10: 1026 | D10: 1457 | E10: 1510 | F10: =IFERROR((E10/C10)^(1/2)-1,0) -> 0.21315081
B11: Depreciation | C11: 3476 | D11: 4225 | E11: 4678 | F11: =IFERROR((E11/C11)^(1/2)-1,0) -> 0.1600861
B12: Interest Expenses | C12: 200 | D12: 284 | E12: 470 | F12: =IFERROR((E12/C12)^(1/2)-1,0) -> 0.53297097
B13: Total Expenses | C13: =SUM(C8:C12) -> 73004 | D13: =SUM(D8:D12) -> 89640 | E13: =SUM(E8:E12) -> 94999
B15: PROFITABILITY
B16: EBIT | C16: =C5-C13 -> 48637 | D16: =D5-D13 -> 57127 | E16: =E5-E13 -> 58671
B17: EBIT Margin % | C17: =IFERROR(C16/C5,0) -> 0.39984051 | D17: =IFERROR(D16/D5,0) -> 0.389236 | E17: =IFERROR(E16/E5,0) -> 0.38179866
B18: Profit Before Tax | C18: 30110 | D18: 33322 | E18: 35988 | F18: =IFERROR((E18/C18)^(1/2)-1,0) -> 0.093260049
B19: Tax Expense | C19: 7964 | D19: 9214 | E19: 9740 | F19: =IFERROR((E19/C19)^(1/2)-1,0) -> 0.10589489
B20: Net Profit | C20: 22110 | D20: 24095 | E20: 26233 | F20: =IFERROR((E20/C20)^(1/2)-1,0) -> 0.089255116
B21: PAT Margin % | C21: =IFERROR(C20/C5,0) -> 0.18176437 | D21: =IFERROR(D20/D5,0) -> 0.16417178 | E21: =IFERROR(E20/E5,0) -> 0.17070996

Sheet Budget Assumption
B2: FY 2025 BUDGET ASSUMPTIONS - INFOSYS LIMITED
B4: Line Item | C4: FY 2024 Actual | D4: Historical CAGR % | E4: Assumption | F4: FY 2025 Budget
B5: Revenue from Operations | C5: ='Raw Data'!E5 -> 153670 | D5: ='Raw Data'!F5 -> 0.12396957 | E5: 0.08 | F5: =C5*(1+E5) -> 165963.6
B6: Employee Cost | C6: ='Raw Data'!E8 -> 82636 | D6: ='Raw Data'!F8 -> 0.13633095 | E6: =5% -> 0.05 | F6: =C6*(1+E6) -> 86767.8
B7: Selling and Admin | C7: ='Raw Data'!E9 -> 5705 | D7: ='Raw Data'!F9 -> 0.15117473 | E7: =6% -> 0.06 | F7: =C7*(1+E7) -> 6047.3
B8: Other Expenses | C8: ='Raw Data'!E10 -> 1510 | D8: ='Raw Data'!F10 -> 0.21315081 | E8: 0.06 | F8: =C8*(1+E8) -> 1600.6
B9: Depreciation | C9: ='Raw Data'!E11 -> 4678 | D9: ='Raw Data'!F11 -> 0.1600861 | E9: 0.05 | F9: =C9*(1+E9) -> 4911.9
B10: Interest Expenses | C10: ='Raw Data'!E12 -> 470 | D10: ='Raw Data'!F12 -> 0.53297097 | E10: 0.05 | F10: =C10*(1+E10) -> 493.5
B11: Effective Tax Rate | C11: 0.25 | D11: 0.25 | E11: 0.25 | F11: 0.25
B12: Total Expenses Budget | F12: =SUM(F6:F10) -> 99821.1
B13: EBIT Budget | F13: =F5-F12 -> 66142.5
B14: PBT Budget | C14: ='Raw Data'!E18 -> 35988 | D14: ='Raw Data'!F18 -> 0.093260049 | E14: =D14 -> 0.093260049 | F14: =C14*(1+E14) -> 39344.243
B15: Tax Expense Budget | F15: =F14*F11 -> 9836.0607
B16: PAT Budget | F16: =F14-F15 -> 29508.182

Sheet Variance Analysis
B2: ACTUAL VS BUDGET VARIANCE ANALYSIS - INFOSYS FY 2025
B4: Line Item | C4: FY 2025 Budget | D4: FY 2025 Actual | E4: Variance | F4: Variance % | G4: F/U | H4: FY 2024 Actual | I4: YoY Growth %
A5: # | B5: REVENUE
B6: Revenue from Operations | C6: ='Budget Assumption'!F5 -> 165963.6 | D6: 162990 | E6: =D6-C6 -> -2973.6 | F6: =IFERROR((D6-C6)/ABS(C6),0) -> -0.017917182 | G6: =IF(E6>0,"F","U") -> U | H6: ='Raw Data'!E5 -> 153670 | I6: =IFERROR((D6-H6)/ABS(H6),0) -> 0.060649444
A8: # | B8: EXPENSES
B9: Employee Cost | C9: ='Budget Assumption'!F6 -> 86767.8 | D9: 85968 | E9: =D9-C9 -> -799.8 | F9: =IFERROR((D9-C9)/ABS(C9),0) -> -0.0092177052 | G9: =IF(E9<0,"F","U") -> F | H9: ='Raw Data'!E8 -> 82636 | I9: =IFERROR((D9-H9)/ABS(H9),0) -> 0.04032141
B10: Selling and Admin | C10: ='Budget Assumption'!F7 -> 6047.3 | D10: 6039 | E10: =D10-C10 -> -8.3 | F10: =IFERROR((D10-C10)/ABS(C10),0) -> -0.0013725134 | G10: =IF(E10<0,"F","U") -> F | H10: ='Raw Data'!E9 -> 5705 | I10: =IFERROR((D10-H10)/ABS(H10),0) -> 0.058545136
B11: Other Expenses | C11: ='Budget Assumption'!F8 -> 1600.6 | D11: 1130 | E11: =D11-C11 -> -470.6 | F11: =IFERROR((D11-C11)/ABS(C11),0) -> -0.29401474 | G11: =IF(E11<0,"F","U") -> F | H11: ='Raw Data'!E10 -> 1510 | I11: =IFERROR((D11-H11)/ABS(H11),0) -> -0.25165563
B12: Depreciation | C12: ='Budget Assumption'!F9 -> 4911.9 | D12: 4812 | E12: =D12-C12 -> -99.9 | F12: =IFERROR((D12-C12)/ABS(C12),0) -> -0.020338362 | G12: =IF(E12<0,"F","U") -> F | H12: ='Raw Data'!E11 -> 4678 | I12: =IFERROR((D12-H12)/ABS(H12),0) -> 0.02864472
B13: Interest Cost | C13: ='Budget Assumption'!F10 -> 493.5 | D13: 416 | E13: =D13-C13 -> -77.5 | F13: =IFERROR((D13-C13)/ABS(C13),0) -> -0.15704154 | G13: =IF(E13<0,"F","U") -> F | H13: ='Raw Data'!E12 -> 470 | I13: =IFERROR((D13-H13)/ABS(H13),0) -> -0.11489362 | K13: z
B14: Total Expenses | C14: =SUM(C9:C13) -> 99821.1 | D14: =SUM(D9:D13) -> 98365 | E14: =D14-C14 -> -1456.1 | F14: =(D14-C14)/C14 -> -0.014587096
A16: # | B16: PROFITABILITY | L16: z
B17: EBIT | C17: =C6-C14 -> 66142.5 | D17: =D6-D14 -> 64625 | E17: =D17-C17 -> -1517.5 | F17: =IFERROR((D17-C17)/ABS(C17),0) -> -0.022942888 | G17: =IF(E17>0,"F","U") -> U
B18: EBIT Margin % | C18: =IFERROR(C17/C6,0) -> 0.39853619 | D18: =IFERROR(D17/D6,0) -> 0.39649672 | E18: =D18-C18 -> -0.0020394675 | F18: =IFERROR((D18-C18)/ABS(C18),0) -> -0.0051173959 | G18: =IF(E18>0,"F","U") -> U
B19: Profit Before Tax | C19: ='Budget Assumption'!F14 -> 39344.243 | D19: 37608 | E19: =D19-C19 -> -1736.2427 | F19: =IFERROR((D19-C19)/ABS(C19),0) -> -0.044129523 | G19: =IF(E19>0,"F","U") -> U | H19: ='Raw Data'!E18 -> 35988 | I19: =IFERROR((D19-H19)/ABS(H19),0) -> 0.045015005
B20: Tax Expense | C20: ='Budget Assumption'!F15 -> 9836.0607 | D20: 10858 | E20: =D20-C20 -> 1021.9393 | F20: =IFERROR((D20-C20)/ABS(C20),0) -> 0.10389722 | G20: =IF(E20>0,"F","U") -> F | H20: ='Raw Data'!E19 -> 9740 | I20: =IFERROR((D20-H20)/ABS(H20),0) -> 0.11478439
B21: Net Profit | C21: ='Budget Assumption'!F16 -> 29508.182 | D21: 26713 | E21: =D21-C21 -> -2795.182 | F21: =IFERROR((D21-C21)/ABS(C21),0) -> -0.094725659 | G21: =IF(E21>0,"F","U") -> U | H21: ='Raw Data'!E20 -> 26233 | I21: =IFERROR((D21-H21)/ABS(H21),0) -> 0.018297564
B22: PAT Margin % | C22: =IFERROR(C21/C6,0) -> 0.17779912 | D22: =IFERROR(D21/D6,0) -> 0.16389349 | E22: =D22-C22 -> -0.013905629 | F22: =IFERROR((D22-C22)/ABS(C22),0) -> -0.078209776 | G22: =IF(E22>0,"F","U") -> U

Sheet CFO Commentary
B2: FP&A MANAGEMENT COMMENTARY - FY INFOSYS 2025
B4: REVENUE PERFORMANCE
B5: Revenue from Operations for FY 2025 came in at ₹1,62,990 Cr, marginally below the budget of ₹1,65,964 Cr by ₹2,974 Cr (-1.8%), though this still represents a healthy YoY growth of 6.1% over FY 2024 actuals of ₹1,53,670 Cr. The shortfall against budget is largely due to the aggressive 8% growth assumption in the plan, which did not fully account for the moderation in IT spending across key geographies. On a 3-year basis, revenue has grown at a CAGR of ~12.4%, reflecting sustained long-term business momentum.
B7: EXPENSE PERFORMANCE
B8: Total expenses for FY 2025 were ₹98,365 Cr, coming in ₹1,456 Cr below the budget of ₹99,821 Cr — a favourable variance of 1.5% — reflecting strong cost discipline across all expense lines. Employee cost at ₹85,968 Cr was slightly below the budget of ₹86,768 Cr (-0.9%), a positive outcome given the historical 3-year CAGR of 13.6% on this line.
B10: PROFITABILITY PERFORMANCE
B11: EBIT for FY 2025 was ₹64,625 Cr against a budget of ₹66,143 Cr, a shortfall of ₹1,518 Cr (-2.3%), with EBIT margin at 39.6% versus budgeted 39.9% — a compression of just 20 basis points. Profit Before Tax came in at ₹37,608 Cr against a revised budget of ₹39,344 Cr (-4.4%), with the budget now based on Infosys's own historical PBT CAGR of 9.3% for a more realistic comparison.
